beetsplug/vibenet.py
vibenet/__init__.py
vibenet/artifacts/efficientnet_model.onnx
vibenet/backends.py
vibenet/cli.py
vibenet/core.py
vibenet/models/__init__.py
vibenet/models/student.py
vibenet/models/teacher.py
vibenet/pann/__init__.py
vibenet/pann/models.py
vibenet/pann/pytorch_utils.py
vibenet/train/dataset.py
vibenet/train/train_utils.py
vibenet/utils.py
vibenet-0.1.0.dist-info/LICENSE
vibenet-0.1.0.dist-info/METADATA
vibenet-0.1.0.dist-info/WHEEL
vibenet-0.1.0.dist-info/entry_points.txt
vibenet-0.1.0.dist-info/RECORD
