Metadata-Version: 2.3
Name: vibenet
Version: 0.1.0
Summary: A Python tool for music emotion and perceptual feature prediction
License: GPL-3.0-or-later
Author: Jaeheon Shim
Author-email: git@jaeheonshim.com
Requires-Python: >=3.8
Classifier: Programming Language :: Python :: 3
Classifier: Operating System :: OS Independent
Requires-Dist: audioread (>=3.0.1,<4.0.0)
Requires-Dist: librosa (>=0.11.0,<0.12.0)
Requires-Dist: onnxruntime (>=1.22.1,<2.0.0)
Requires-Dist: pydub (>=0.25.1,<0.26.0)
Requires-Dist: typer (>=0.16.0,<0.17.0)
Project-URL: Homepage, https://github.com/jaeheonshim/vibenet
